uni_transform/__init__.py
uni_transform/main.py
uni_transform/py.typed
uni_transform-0.2.0.dist-info/licenses/LICENSE
uni_transform-0.2.0.dist-info/METADATA
uni_transform-0.2.0.dist-info/WHEEL
uni_transform-0.2.0.dist-info/top_level.txt
uni_transform-0.2.0.dist-info/RECORD
